sweetrpg_kv_objects/__init__.py
sweetrpg_kv_objects/constants.py
sweetrpg_kv_objects/api/__init__.py
sweetrpg_kv_objects/api/key/__init__.py
sweetrpg_kv_objects/api/key/schema.py
sweetrpg_kv_objects/api/snapshot/__init__.py
sweetrpg_kv_objects/api/snapshot/schema.py
sweetrpg_kv_objects/api/store/__init__.py
sweetrpg_kv_objects/api/store/schema.py
sweetrpg_kv_objects/api/value/__init__.py
sweetrpg_kv_objects/api/value/schema.py
sweetrpg_kv_objects/db/__init__.py
sweetrpg_kv_objects/db/embedded/__init__.py
sweetrpg_kv_objects/db/embedded/property/__init__.py
sweetrpg_kv_objects/db/embedded/property/document.py
sweetrpg_kv_objects/db/embedded/property/schema.py
sweetrpg_kv_objects/db/embedded/tag/__init__.py
sweetrpg_kv_objects/db/embedded/tag/document.py
sweetrpg_kv_objects/db/embedded/tag/schema.py
sweetrpg_kv_objects/db/key/__init__.py
sweetrpg_kv_objects/db/key/document.py
sweetrpg_kv_objects/db/key/schema.py
sweetrpg_kv_objects/db/snapshot/__init__.py
sweetrpg_kv_objects/db/snapshot/document.py
sweetrpg_kv_objects/db/snapshot/schema.py
sweetrpg_kv_objects/db/store/__init__.py
sweetrpg_kv_objects/db/store/document.py
sweetrpg_kv_objects/db/store/schema.py
sweetrpg_kv_objects/db/value/__init__.py
sweetrpg_kv_objects/db/value/document.py
sweetrpg_kv_objects/db/value/schema.py
sweetrpg_kv_objects/events/__init__.py
sweetrpg_kv_objects/events/expression.py
sweetrpg_kv_objects/events/key.py
sweetrpg_kv_objects/events/value.py
sweetrpg_kv_objects/model/__init__.py
sweetrpg_kv_objects/model/key.py
sweetrpg_kv_objects/model/snapshot.py
sweetrpg_kv_objects/model/store.py
sweetrpg_kv_objects/model/value.py
sweetrpg_kv_objects/model/embedded/__init__.py
sweetrpg_kv_objects/model/embedded/property.py
sweetrpg_kv_objects/model/embedded/tag.py
sweetrpg_kv_objects/utils/__init__.py
sweetrpg_kv_objects/utils/user.py
sweetrpg_kv_objects-0.0.52.dist-info/LICENSE
sweetrpg_kv_objects-0.0.52.dist-info/METADATA
sweetrpg_kv_objects-0.0.52.dist-info/WHEEL
sweetrpg_kv_objects-0.0.52.dist-info/entry_points.txt
sweetrpg_kv_objects-0.0.52.dist-info/top_level.txt
sweetrpg_kv_objects-0.0.52.dist-info/RECORD
