Metadata-Version: 2.1
Name: sweetrpg-kv-objects
Version: 0.0.52
Home-page: https://sweetrpg.com
Author: Paul Schifferer
Author-email: dm@sweetrpg.com
License: MIT
Project-URL: Documentation, https://sweetrpg.github.io/kv-objects
Classifier: Development Status :: 3 - Alpha
Classifier: Environment :: Web Environment
Classifier: Framework :: Flask
Classifier: Intended Audience :: Developers
Classifier: License :: OSI Approved :: MIT License
Classifier: Operating System :: OS Independent
Classifier: Programming Language :: Python
Classifier: Topic :: Software Development :: Libraries :: Application Frameworks
License-File: LICENSE
Requires-Dist: Flask~=3.0
Requires-Dist: marshmallow-jsonapi~=0.24
Requires-Dist: mongoengine~=0.27
Requires-Dist: sweetrpg-api-core
Requires-Dist: sweetrpg-db
Requires-Dist: sweetrpg-model-core
